euclv/SVMK18.dat
euclv/__init__.py
euclv-0.1.dist-info/METADATA
euclv-0.1.dist-info/RECORD
euclv-0.1.dist-info/WHEEL
euclv-0.1.dist-info/top_level.txt
euclv-0.1.dist-info/zip-safe
